huaweicloudsdkcloudide/__init__.py
huaweicloudsdkcloudide/v2/__init__.py
huaweicloudsdkcloudide/v2/cloudide_async_client.py
huaweicloudsdkcloudide/v2/cloudide_client.py
huaweicloudsdkcloudide/v2/model/__init__.py
huaweicloudsdkcloudide/v2/model/acceptance_schema.py
huaweicloudsdkcloudide/v2/model/account_status.py
huaweicloudsdkcloudide/v2/model/add_extension_evaluation_reply_request.py
huaweicloudsdkcloudide/v2/model/add_extension_evaluation_reply_response.py
huaweicloudsdkcloudide/v2/model/add_extension_evaluation_request.py
huaweicloudsdkcloudide/v2/model/add_extension_evaluation_response.py
huaweicloudsdkcloudide/v2/model/add_extension_star_request.py
huaweicloudsdkcloudide/v2/model/add_extension_star_response.py
huaweicloudsdkcloudide/v2/model/attributes.py
huaweicloudsdkcloudide/v2/model/chat_request_message.py
huaweicloudsdkcloudide/v2/model/chat_result_request_message.py
huaweicloudsdkcloudide/v2/model/check_instance_access_request.py
huaweicloudsdkcloudide/v2/model/check_instance_access_response.py
huaweicloudsdkcloudide/v2/model/check_malicious_extension_evaluation_request.py
huaweicloudsdkcloudide/v2/model/check_malicious_extension_evaluation_response.py
huaweicloudsdkcloudide/v2/model/check_name_request.py
huaweicloudsdkcloudide/v2/model/check_name_response.py
huaweicloudsdkcloudide/v2/model/check_result.py
huaweicloudsdkcloudide/v2/model/check_result_error.py
huaweicloudsdkcloudide/v2/model/code_arts_ide_online_extension_version_property.py
huaweicloudsdkcloudide/v2/model/create_acceptance_request.py
huaweicloudsdkcloudide/v2/model/create_acceptance_response.py
huaweicloudsdkcloudide/v2/model/create_apply_request.py
huaweicloudsdkcloudide/v2/model/create_apply_response.py
huaweicloudsdkcloudide/v2/model/create_event_request.py
huaweicloudsdkcloudide/v2/model/create_event_response.py
huaweicloudsdkcloudide/v2/model/create_extension_authorization_request.py
huaweicloudsdkcloudide/v2/model/create_extension_authorization_response.py
huaweicloudsdkcloudide-3.1.184.dist-info/METADATA
huaweicloudsdkcloudide-3.1.184.dist-info/WHEEL
huaweicloudsdkcloudide-3.1.184.dist-info/licenses/LICENSE
huaweicloudsdkcloudide-3.1.184.dist-info/RECORD
